petal_app_manager-0.1.60.dist-info/METADATA
petal_app_manager-0.1.60.dist-info/WHEEL
petal_app_manager-0.1.60.dist-info/entry_points.txt
petal_app_manager-0.1.60.dist-info/licenses/LICENSE.md
petal_app_manager/__init__.py
petal_app_manager/api/__init__.py
petal_app_manager/api/admin_ui.py
petal_app_manager/api/bucket_api.py
petal_app_manager/api/cloud_api.py
petal_app_manager/api/config_api.py
petal_app_manager/api/health.py
petal_app_manager/api/mavftp_api.py
petal_app_manager/api/mqtt_api.py
petal_app_manager/api/proxy_info.py
petal_app_manager/config.py
petal_app_manager/examples/example_mqtt_usage.py
petal_app_manager/examples/example_redis_petal.py
petal_app_manager/examples/hear_fc_communication_example.py
petal_app_manager/examples/integration_test_hear_fc.py
petal_app_manager/examples/logging_example_petal.py
petal_app_manager/examples/mavlink_burst_filtering_example.py
petal_app_manager/examples/proxy_usage_example.py
petal_app_manager/examples/redis_usage_examples.py
petal_app_manager/examples/simple_redis_petal.py
petal_app_manager/health_service.py
petal_app_manager/logger.py
petal_app_manager/main.py
petal_app_manager/models/__init__.py
petal_app_manager/models/health.py
petal_app_manager/models/mavlink.py
petal_app_manager/models/mqtt.py
petal_app_manager/organization_manager.py
petal_app_manager/plugins/__init__.py
petal_app_manager/plugins/base.py
petal_app_manager/plugins/decorators.py
petal_app_manager/plugins/loader.py
petal_app_manager/proxies/__init__.py
petal_app_manager/proxies/base.py
petal_app_manager/proxies/bucket.py
petal_app_manager/proxies/cloud.py
petal_app_manager/proxies/external.py
petal_app_manager/proxies/localdb.py
petal_app_manager/proxies/mqtt.py
petal_app_manager/proxies/org_utils.py
petal_app_manager/proxies/redis.py
petal_app_manager/utils/__init__.py
petal_app_manager/utils/log_tool.py
petal_app_manager/utils/machineid_arm
petal_app_manager/utils/machineid_x86
petal_app_manager-0.1.60.dist-info/RECORD
