Metadata-Version: 2.1
Name: petal-app-manager
Version: 0.1.60
Summary: A FastAPI interface for loading, managing and running Droneleaf Petal applications
Author-Email: Khalil Al Handawi <khalil.alhandawi@droneleaf.io>
License: LICENSE.md
Requires-Python: >=3.10
Requires-Dist: tqdm>=4.67.1
Requires-Dist: tabulate>=0.9.0
Requires-Dist: fastapi[standard]>=0.115.12
Requires-Dist: uvicorn[standard]>=0.34.3
Requires-Dist: redis>=6.2.0
Requires-Dist: boto3>=1.39.14
Requires-Dist: requests>=2.32.4
